<?xml version="1.0" encoding="UTF-8" standalone="no"?>
<!DOCTYPE tiles-definitions PUBLIC "-//Apache Software Foundation//DTD Tiles Configuration 2.1//EN" "http://tiles.apache.org/dtds/tiles-config_2_1.dtd">
<tiles-definitions>

    <definition extends="manager" name="manager/index">
        <put-attribute name="body" value="/WEB-INF/views/manager/index.jspx" />
    </definition>

    <definition extends="manager" name="manager/emailConfirmed">
        <put-attribute name="body" value="/WEB-INF/views/manager/emailConfirmed.jspx" />
    </definition>

    <definition extends="manager" name="manager/linkNotValid">
        <put-attribute name="body" value="/WEB-INF/views/manager/linkNotValid.jspx" />
    </definition>
    
    <definition extends="manager" name="manager/linkActive">
        <put-attribute name="body" value="/WEB-INF/views/manager/linkActive.jspx" />
    </definition>
    
        <definition extends="manager" name="manager/linkSent">
        <put-attribute name="body" value="/WEB-INF/views/manager/linkSent.jspx" />
    </definition>

</tiles-definitions>
